{
  "name": "MueckenAmeisen-G1.636388888888889-399-6c67767f",
  "generation": 0.6363888888888889,
  "mixture": {
    "ameisen_schwarm": 36.0,
    "tiefsee_leuchtnetz": 4.71,
    "quorum_sensing": 8.3,
    "muecken_wolke": 39.78,
    "schnecken_chemospur": 11.21
  },
  "fitness": 0.42508364972447715,
  "timestamp": "20260404_142111",
  "graph_data": {
    "directed": true,
    "multigraph": false,
    "graph": {},
    "nodes": [
      {
        "type": "PlasticityGate",
        "bio_influence": {
          "ameisen_schwarm": 36.0,
          "tiefsee_leuchtnetz": 4.71,
          "quorum_sensing": 8.3,
          "muecken_wolke": 39.78,
          "schnecken_chemospur": 11.21
        },
        "id": 0
      },
      {
        "type": "SwarmFFN",
        "bio_influence": {
          "ameisen_schwarm": 36.0,
          "tiefsee_leuchtnetz": 4.71,
          "quorum_sensing": 8.3,
          "muecken_wolke": 39.78,
          "schnecken_chemospur": 11.21
        },
        "id": 1
      },
      {
        "type": "SwarmFFN",
        "bio_influence": {
          "ameisen_schwarm": 36.0,
          "tiefsee_leuchtnetz": 4.71,
          "quorum_sensing": 8.3,
          "muecken_wolke": 39.78,
          "schnecken_chemospur": 11.21
        },
        "id": 2
      },
      {
        "type": "StandardMLP",
        "bio_influence": {
          "ameisen_schwarm": 36.0,
          "tiefsee_leuchtnetz": 4.71,
          "quorum_sensing": 8.3,
          "muecken_wolke": 39.78,
          "schnecken_chemospur": 11.21
        },
        "id": 3
      },
      {
        "type": "SwarmFFN",
        "bio_influence": {
          "ameisen_schwarm": 36.0,
          "tiefsee_leuchtnetz": 4.71,
          "quorum_sensing": 8.3,
          "muecken_wolke": 39.78,
          "schnecken_chemospur": 11.21
        },
        "id": 4
      },
      {
        "type": "PlasticityGate",
        "bio_influence": {
          "ameisen_schwarm": 36.0,
          "tiefsee_leuchtnetz": 4.71,
          "quorum_sensing": 8.3,
          "muecken_wolke": 39.78,
          "schnecken_chemospur": 11.21
        },
        "id": 5
      },
      {
        "type": "PlasticityGate",
        "bio_influence": {
          "ameisen_schwarm": 36.0,
          "tiefsee_leuchtnetz": 4.71,
          "quorum_sensing": 8.3,
          "muecken_wolke": 39.78,
          "schnecken_chemospur": 11.21
        },
        "id": 6
      },
      {
        "type": "StandardMLP",
        "bio_influence": {
          "ameisen_schwarm": 36.0,
          "tiefsee_leuchtnetz": 4.71,
          "quorum_sensing": 8.3,
          "muecken_wolke": 39.78,
          "schnecken_chemospur": 11.21
        },
        "id": 7
      },
      {
        "type": "PlasticityGate",
        "bio_influence": {
          "ameisen_schwarm": 36.0,
          "tiefsee_leuchtnetz": 4.71,
          "quorum_sensing": 8.3,
          "muecken_wolke": 39.78,
          "schnecken_chemospur": 11.21
        },
        "id": 8
      },
      {
        "type": "StandardMLP",
        "bio_influence": {
          "ameisen_schwarm": 36.0,
          "tiefsee_leuchtnetz": 4.71,
          "quorum_sensing": 8.3,
          "muecken_wolke": 39.78,
          "schnecken_chemospur": 11.21
        },
        "id": 9
      },
      {
        "type": "PlasticityGate",
        "bio_influence": {
          "ameisen_schwarm": 36.0,
          "tiefsee_leuchtnetz": 4.71,
          "quorum_sensing": 8.3,
          "muecken_wolke": 39.78,
          "schnecken_chemospur": 11.21
        },
        "id": 10
      },
      {
        "type": "SwarmFFN",
        "bio_influence": {
          "ameisen_schwarm": 36.0,
          "tiefsee_leuchtnetz": 4.71,
          "quorum_sensing": 8.3,
          "muecken_wolke": 39.78,
          "schnecken_chemospur": 11.21
        },
        "id": 11
      },
      {
        "type": "SwarmFFN",
        "bio_influence": {
          "ameisen_schwarm": 36.0,
          "tiefsee_leuchtnetz": 4.71,
          "quorum_sensing": 8.3,
          "muecken_wolke": 39.78,
          "schnecken_chemospur": 11.21
        },
        "id": 12
      },
      {
        "type": "PlasticityGate",
        "bio_influence": {
          "ameisen_schwarm": 36.0,
          "tiefsee_leuchtnetz": 4.71,
          "quorum_sensing": 8.3,
          "muecken_wolke": 39.78,
          "schnecken_chemospur": 11.21
        },
        "id": 13
      },
      {
        "type": "StandardMLP",
        "bio_influence": {
          "ameisen_schwarm": 36.0,
          "tiefsee_leuchtnetz": 4.71,
          "quorum_sensing": 8.3,
          "muecken_wolke": 39.78,
          "schnecken_chemospur": 11.21
        },
        "id": 14
      },
      {
        "type": "SwarmFFN",
        "bio_influence": {
          "ameisen_schwarm": 36.0,
          "tiefsee_leuchtnetz": 4.71,
          "quorum_sensing": 8.3,
          "muecken_wolke": 39.78,
          "schnecken_chemospur": 11.21
        },
        "id": 15
      },
      {
        "type": "StandardMLP",
        "bio_influence": {
          "ameisen_schwarm": 36.0,
          "tiefsee_leuchtnetz": 4.71,
          "quorum_sensing": 8.3,
          "muecken_wolke": 39.78,
          "schnecken_chemospur": 11.21
        },
        "id": 16
      },
      {
        "type": "SwarmFFN",
        "bio_influence": {
          "ameisen_schwarm": 36.0,
          "tiefsee_leuchtnetz": 4.71,
          "quorum_sensing": 8.3,
          "muecken_wolke": 39.78,
          "schnecken_chemospur": 11.21
        },
        "id": 17
      },
      {
        "type": "PlasticityGate",
        "bio_influence": {
          "ameisen_schwarm": 36.0,
          "tiefsee_leuchtnetz": 4.71,
          "quorum_sensing": 8.3,
          "muecken_wolke": 39.78,
          "schnecken_chemospur": 11.21
        },
        "id": 18
      },
      {
        "type": "StandardMLP",
        "bio_influence": {
          "ameisen_schwarm": 36.0,
          "tiefsee_leuchtnetz": 4.71,
          "quorum_sensing": 8.3,
          "muecken_wolke": 39.78,
          "schnecken_chemospur": 11.21
        },
        "id": 19
      },
      {
        "type": "StandardMLP",
        "bio_influence": {
          "ameisen_schwarm": 36.0,
          "tiefsee_leuchtnetz": 4.71,
          "quorum_sensing": 8.3,
          "muecken_wolke": 39.78,
          "schnecken_chemospur": 11.21
        },
        "id": 20
      },
      {
        "type": "PlasticityGate",
        "bio_influence": {
          "ameisen_schwarm": 36.0,
          "tiefsee_leuchtnetz": 4.71,
          "quorum_sensing": 8.3,
          "muecken_wolke": 39.78,
          "schnecken_chemospur": 11.21
        },
        "id": 21
      },
      {
        "type": "StandardMLP",
        "bio_influence": {
          "ameisen_schwarm": 36.0,
          "tiefsee_leuchtnetz": 4.71,
          "quorum_sensing": 8.3,
          "muecken_wolke": 39.78,
          "schnecken_chemospur": 11.21
        },
        "id": 22
      },
      {
        "type": "StandardMLP",
        "bio_influence": {
          "ameisen_schwarm": 36.0,
          "tiefsee_leuchtnetz": 4.71,
          "quorum_sensing": 8.3,
          "muecken_wolke": 39.78,
          "schnecken_chemospur": 11.21
        },
        "id": 23
      },
      {
        "type": "PlasticityGate",
        "bio_influence": {
          "ameisen_schwarm": 36.0,
          "tiefsee_leuchtnetz": 4.71,
          "quorum_sensing": 8.3,
          "muecken_wolke": 39.78,
          "schnecken_chemospur": 11.21
        },
        "id": 24
      },
      {
        "type": "SwarmFFN",
        "bio_influence": {
          "ameisen_schwarm": 36.0,
          "tiefsee_leuchtnetz": 4.71,
          "quorum_sensing": 8.3,
          "muecken_wolke": 39.78,
          "schnecken_chemospur": 11.21
        },
        "id": 25
      },
      {
        "type": "PlasticityGate",
        "bio_influence": {
          "ameisen_schwarm": 36.0,
          "tiefsee_leuchtnetz": 4.71,
          "quorum_sensing": 8.3,
          "muecken_wolke": 39.78,
          "schnecken_chemospur": 11.21
        },
        "id": 26
      },
      {
        "type": "AttentionHead",
        "bio_influence": {
          "ameisen_schwarm": 36.0,
          "tiefsee_leuchtnetz": 4.71,
          "quorum_sensing": 8.3,
          "muecken_wolke": 39.78,
          "schnecken_chemospur": 11.21
        },
        "id": 27
      },
      {
        "type": "PlasticityGate",
        "bio_influence": {
          "ameisen_schwarm": 36.0,
          "tiefsee_leuchtnetz": 4.71,
          "quorum_sensing": 8.3,
          "muecken_wolke": 39.78,
          "schnecken_chemospur": 11.21
        },
        "id": 28
      },
      {
        "type": "PlasticityGate",
        "bio_influence": {
          "ameisen_schwarm": 36.0,
          "tiefsee_leuchtnetz": 4.71,
          "quorum_sensing": 8.3,
          "muecken_wolke": 39.78,
          "schnecken_chemospur": 11.21
        },
        "id": 29
      },
      {
        "type": "SwarmFFN",
        "bio_influence": {
          "ameisen_schwarm": 36.0,
          "tiefsee_leuchtnetz": 4.71,
          "quorum_sensing": 8.3,
          "muecken_wolke": 39.78,
          "schnecken_chemospur": 11.21
        },
        "id": 30
      },
      {
        "type": "PlasticityGate",
        "bio_influence": {
          "ameisen_schwarm": 36.0,
          "tiefsee_leuchtnetz": 4.71,
          "quorum_sensing": 8.3,
          "muecken_wolke": 39.78,
          "schnecken_chemospur": 11.21
        },
        "id": 31
      },
      {
        "type": "StandardMLP",
        "bio_influence": {
          "ameisen_schwarm": 36.0,
          "tiefsee_leuchtnetz": 4.71,
          "quorum_sensing": 8.3,
          "muecken_wolke": 39.78,
          "schnecken_chemospur": 11.21
        },
        "id": 32
      }
    ],
    "edges": [
      {
        "weight": 1.0577520428882634,
        "type": "forward",
        "source": 0,
        "target": 3
      },
      {
        "weight": 0.7015420369994949,
        "type": "forward",
        "source": 0,
        "target": 13
      },
      {
        "weight": 0.6304249093184878,
        "type": "forward",
        "source": 0,
        "target": 18
      },
      {
        "weight": 1.0269972580855125,
        "type": "forward",
        "source": 0,
        "target": 23
      },
      {
        "weight": 0.5541900663376679,
        "type": "forward",
        "source": 0,
        "target": 25
      },
      {
        "weight": 0.6676639392352035,
        "type": "forward",
        "source": 0,
        "target": 27
      },
      {
        "weight": 1.4028213956517388,
        "type": "forward",
        "source": 0,
        "target": 29
      },
      {
        "weight": 1.1076135996083862,
        "type": "forward",
        "source": 0,
        "target": 32
      },
      {
        "weight": 0.7115679569217096,
        "type": "forward",
        "source": 1,
        "target": 5
      },
      {
        "weight": 1.0554624621420334,
        "type": "forward",
        "source": 1,
        "target": 12
      },
      {
        "weight": 1.0220228169290206,
        "type": "forward",
        "source": 1,
        "target": 18
      },
      {
        "weight": 1.4032325652192563,
        "type": "forward",
        "source": 1,
        "target": 19
      },
      {
        "weight": 1.3298705652849554,
        "type": "forward",
        "source": 1,
        "target": 22
      },
      {
        "weight": 1.4203895193011573,
        "type": "forward",
        "source": 1,
        "target": 23
      },
      {
        "weight": 1.4232732311532104,
        "type": "forward",
        "source": 1,
        "target": 25
      },
      {
        "weight": 1.0641281101015183,
        "type": "forward",
        "source": 1,
        "target": 27
      },
      {
        "weight": 0.5714505451218655,
        "type": "forward",
        "source": 1,
        "target": 32
      },
      {
        "weight": 0.7358440783708717,
        "type": "forward",
        "source": 2,
        "target": 4
      },
      {
        "weight": 1.3139796974658653,
        "type": "forward",
        "source": 2,
        "target": 5
      },
      {
        "weight": 1.3825991795673698,
        "type": "forward",
        "source": 2,
        "target": 12
      },
      {
        "weight": 1.25705900916493,
        "type": "forward",
        "source": 2,
        "target": 15
      },
      {
        "weight": 0.8617282636338969,
        "type": "forward",
        "source": 2,
        "target": 24
      },
      {
        "weight": 1.419447148796929,
        "type": "forward",
        "source": 2,
        "target": 25
      },
      {
        "weight": 0.542773066954104,
        "type": "forward",
        "source": 2,
        "target": 26
      },
      {
        "weight": 1.31008471271382,
        "type": "forward",
        "source": 3,
        "target": 7
      },
      {
        "weight": 0.8320816174978007,
        "type": "forward",
        "source": 3,
        "target": 11
      },
      {
        "weight": 1.2128742496150402,
        "type": "forward",
        "source": 3,
        "target": 25
      },
      {
        "weight": 0.7099808429483991,
        "type": "forward",
        "source": 4,
        "target": 5
      },
      {
        "weight": 0.6158255621750178,
        "type": "forward",
        "source": 4,
        "target": 8
      },
      {
        "weight": 1.4300960459059366,
        "type": "forward",
        "source": 4,
        "target": 11
      },
      {
        "weight": 1.341534786613869,
        "type": "forward",
        "source": 4,
        "target": 19
      },
      {
        "weight": 1.2326647804374633,
        "type": "forward",
        "source": 4,
        "target": 21
      },
      {
        "weight": 1.4509281258876803,
        "type": "forward",
        "source": 4,
        "target": 23
      },
      {
        "weight": 0.8181834160415514,
        "type": "forward",
        "source": 4,
        "target": 24
      },
      {
        "weight": 1.0654421743696851,
        "type": "forward",
        "source": 4,
        "target": 25
      },
      {
        "weight": 1.3610726821477312,
        "type": "forward",
        "source": 4,
        "target": 28
      },
      {
        "weight": 1.4506128354317007,
        "type": "forward",
        "source": 4,
        "target": 29
      },
      {
        "weight": 0.5570605727233623,
        "type": "forward",
        "source": 5,
        "target": 13
      },
      {
        "weight": 0.9243223809832875,
        "type": "forward",
        "source": 5,
        "target": 15
      },
      {
        "weight": 0.9843533498858218,
        "type": "forward",
        "source": 5,
        "target": 16
      },
      {
        "weight": 0.613219693974853,
        "type": "forward",
        "source": 5,
        "target": 18
      },
      {
        "weight": 1.2422737440697698,
        "type": "forward",
        "source": 5,
        "target": 24
      },
      {
        "weight": 1.090501834382219,
        "type": "forward",
        "source": 5,
        "target": 27
      },
      {
        "weight": 0.99141752146338,
        "type": "forward",
        "source": 5,
        "target": 28
      },
      {
        "weight": 0.9579747683832276,
        "type": "forward",
        "source": 5,
        "target": 29
      },
      {
        "weight": 0.8923242711862578,
        "type": "forward",
        "source": 5,
        "target": 31
      },
      {
        "weight": 1.3915361461294768,
        "type": "forward",
        "source": 6,
        "target": 7
      },
      {
        "weight": 1.4200284994624994,
        "type": "forward",
        "source": 6,
        "target": 12
      },
      {
        "weight": 1.062477384476245,
        "type": "forward",
        "source": 6,
        "target": 18
      },
      {
        "weight": 0.9641370070307571,
        "type": "forward",
        "source": 6,
        "target": 24
      },
      {
        "weight": 0.8483496533238176,
        "type": "forward",
        "source": 6,
        "target": 25
      },
      {
        "weight": 0.5775847214154152,
        "type": "forward",
        "source": 6,
        "target": 31
      },
      {
        "weight": 0.9405443299105878,
        "type": "forward",
        "source": 7,
        "target": 12
      },
      {
        "weight": 1.0863467137003948,
        "type": "forward",
        "source": 7,
        "target": 13
      },
      {
        "weight": 0.9124529248060154,
        "type": "forward",
        "source": 7,
        "target": 14
      },
      {
        "weight": 1.2417841743084301,
        "type": "forward",
        "source": 7,
        "target": 24
      },
      {
        "weight": 1.362847162332102,
        "type": "forward",
        "source": 7,
        "target": 26
      },
      {
        "weight": 0.5933026302611535,
        "type": "forward",
        "source": 7,
        "target": 27
      },
      {
        "weight": 0.6303126677996583,
        "type": "forward",
        "source": 7,
        "target": 29
      },
      {
        "weight": 1.359972837402271,
        "type": "forward",
        "source": 7,
        "target": 30
      },
      {
        "weight": 0.6824009447063143,
        "type": "forward",
        "source": 8,
        "target": 9
      },
      {
        "weight": 0.9978360051174465,
        "type": "forward",
        "source": 8,
        "target": 15
      },
      {
        "weight": 0.7987879164432278,
        "type": "forward",
        "source": 8,
        "target": 19
      },
      {
        "weight": 1.4705554150613902,
        "type": "forward",
        "source": 8,
        "target": 21
      },
      {
        "weight": 0.7028906159783612,
        "type": "forward",
        "source": 8,
        "target": 22
      },
      {
        "weight": 1.1747509055215595,
        "type": "forward",
        "source": 8,
        "target": 25
      },
      {
        "weight": 0.8405495369725703,
        "type": "forward",
        "source": 8,
        "target": 26
      },
      {
        "weight": 1.1322989471395406,
        "type": "forward",
        "source": 8,
        "target": 27
      },
      {
        "weight": 1.0977663083444742,
        "type": "forward",
        "source": 8,
        "target": 28
      },
      {
        "weight": 0.719808223453129,
        "type": "forward",
        "source": 8,
        "target": 30
      },
      {
        "weight": 1.1675429981982057,
        "type": "forward",
        "source": 8,
        "target": 31
      },
      {
        "weight": 0.902696533357961,
        "type": "forward",
        "source": 9,
        "target": 10
      },
      {
        "weight": 0.6606249299665838,
        "type": "forward",
        "source": 9,
        "target": 13
      },
      {
        "weight": 0.3070176250932466,
        "type": "feedback",
        "source": 9,
        "target": 25
      },
      {
        "weight": 1.0179994437572026,
        "type": "forward",
        "source": 10,
        "target": 12
      },
      {
        "weight": 0.8350901025673465,
        "type": "forward",
        "source": 10,
        "target": 15
      },
      {
        "weight": 1.019818858025554,
        "type": "forward",
        "source": 10,
        "target": 21
      },
      {
        "weight": 0.7049142669293376,
        "type": "forward",
        "source": 10,
        "target": 23
      },
      {
        "weight": 0.9278745799945884,
        "type": "forward",
        "source": 10,
        "target": 25
      },
      {
        "weight": 1.217930455621499,
        "type": "forward",
        "source": 10,
        "target": 26
      },
      {
        "weight": 0.995187420743572,
        "type": "forward",
        "source": 10,
        "target": 32
      },
      {
        "weight": 1.194369262198783,
        "type": "forward",
        "source": 11,
        "target": 13
      },
      {
        "weight": 0.7125001371501598,
        "type": "forward",
        "source": 11,
        "target": 14
      },
      {
        "weight": 1.182197961076159,
        "type": "forward",
        "source": 11,
        "target": 15
      },
      {
        "weight": 1.060978419756081,
        "type": "forward",
        "source": 11,
        "target": 20
      },
      {
        "weight": 1.2285210054373044,
        "type": "forward",
        "source": 11,
        "target": 25
      },
      {
        "weight": 1.2858686924793383,
        "type": "forward",
        "source": 11,
        "target": 32
      },
      {
        "weight": 0.9626971423470316,
        "type": "forward",
        "source": 12,
        "target": 15
      },
      {
        "weight": 0.8565290127287631,
        "type": "forward",
        "source": 12,
        "target": 21
      },
      {
        "weight": 0.5601639039024245,
        "type": "forward",
        "source": 12,
        "target": 22
      },
      {
        "weight": 1.0277626110023936,
        "type": "forward",
        "source": 12,
        "target": 25
      },
      {
        "weight": 1.382192643231728,
        "type": "forward",
        "source": 12,
        "target": 28
      },
      {
        "weight": 0.5556827078693153,
        "type": "forward",
        "source": 12,
        "target": 30
      },
      {
        "weight": 1.4240685467089111,
        "type": "forward",
        "source": 13,
        "target": 14
      },
      {
        "weight": 0.8399917103566314,
        "type": "forward",
        "source": 13,
        "target": 18
      },
      {
        "weight": 1.0811555082505127,
        "type": "forward",
        "source": 13,
        "target": 23
      },
      {
        "weight": 0.9465273488252044,
        "type": "forward",
        "source": 13,
        "target": 24
      },
      {
        "weight": 1.345412373332723,
        "type": "forward",
        "source": 13,
        "target": 25
      },
      {
        "weight": 0.9134626862709282,
        "type": "forward",
        "source": 13,
        "target": 26
      },
      {
        "weight": 1.4746242120766309,
        "type": "forward",
        "source": 14,
        "target": 15
      },
      {
        "weight": 0.6080139927544491,
        "type": "feedback",
        "source": 14,
        "target": 19
      },
      {
        "weight": 0.5309217187352697,
        "type": "forward",
        "source": 14,
        "target": 22
      },
      {
        "weight": 1.3602771681467383,
        "type": "forward",
        "source": 14,
        "target": 31
      },
      {
        "weight": 0.5980344097903006,
        "type": "forward",
        "source": 15,
        "target": 19
      },
      {
        "weight": 1.4978624461784302,
        "type": "forward",
        "source": 15,
        "target": 24
      },
      {
        "weight": 1.1487802919177268,
        "type": "forward",
        "source": 15,
        "target": 27
      },
      {
        "weight": 0.9234070296538299,
        "type": "forward",
        "source": 16,
        "target": 29
      },
      {
        "weight": 1.197601566594802,
        "type": "forward",
        "source": 16,
        "target": 30
      },
      {
        "weight": 1.2475901487382612,
        "type": "forward",
        "source": 17,
        "target": 21
      },
      {
        "weight": 1.0400485173557668,
        "type": "forward",
        "source": 17,
        "target": 24
      },
      {
        "weight": 0.6647511644570299,
        "type": "forward",
        "source": 17,
        "target": 29
      },
      {
        "weight": 0.9117438441106247,
        "type": "forward",
        "source": 17,
        "target": 31
      },
      {
        "weight": 1.1670815304061586,
        "type": "forward",
        "source": 18,
        "target": 22
      },
      {
        "weight": 0.5550194997925771,
        "type": "forward",
        "source": 19,
        "target": 22
      },
      {
        "weight": 1.014948706234188,
        "type": "forward",
        "source": 19,
        "target": 25
      },
      {
        "weight": 1.4294629118750484,
        "type": "forward",
        "source": 19,
        "target": 27
      },
      {
        "weight": 0.5674553220716666,
        "type": "forward",
        "source": 19,
        "target": 29
      },
      {
        "weight": 0.5920768969864334,
        "type": "forward",
        "source": 20,
        "target": 21
      },
      {
        "weight": 1.473475626143332,
        "type": "forward",
        "source": 20,
        "target": 25
      },
      {
        "weight": 1.4434973449980961,
        "type": "forward",
        "source": 20,
        "target": 27
      },
      {
        "weight": 0.9240773133279979,
        "type": "forward",
        "source": 21,
        "target": 26
      },
      {
        "weight": 1.0558068779699368,
        "type": "forward",
        "source": 21,
        "target": 30
      },
      {
        "weight": 0.7403301331327866,
        "type": "forward",
        "source": 21,
        "target": 31
      },
      {
        "weight": 0.6102238187570144,
        "type": "forward",
        "source": 22,
        "target": 28
      },
      {
        "weight": 0.6650119278322574,
        "type": "forward",
        "source": 23,
        "target": 24
      },
      {
        "weight": 0.8764749335594513,
        "type": "forward",
        "source": 23,
        "target": 28
      },
      {
        "weight": 0.5565091395805111,
        "type": "forward",
        "source": 23,
        "target": 29
      },
      {
        "weight": 0.7727528894511707,
        "type": "forward",
        "source": 25,
        "target": 29
      },
      {
        "weight": 1.454477632092041,
        "type": "forward",
        "source": 25,
        "target": 30
      },
      {
        "weight": 1.2853861015711294,
        "type": "forward",
        "source": 25,
        "target": 32
      },
      {
        "weight": 0.8936115252919906,
        "type": "forward",
        "source": 26,
        "target": 27
      },
      {
        "weight": 1.3925468414971827,
        "type": "forward",
        "source": 27,
        "target": 31
      },
      {
        "weight": 1.0720633035330382,
        "type": "forward",
        "source": 30,
        "target": 32
      },
      {
        "weight": 1.292563352116916,
        "type": "forward",
        "source": 31,
        "target": 32
      }
    ]
  }
}