{
  "name": "PilzAmeisen-G1.636388888888889-706-4a7d7167",
  "generation": 0.6363888888888889,
  "mixture": {
    "virus_mutationsdruck": 3.26,
    "fledermaus_echolot": 0.0,
    "bienen_schwarm": 5.0,
    "elefanten_matriarchat": 6.33,
    "honigbienentanz": 16.87,
    "ameisen_blattschneider": 19.76,
    "mensch_gehirn": 1.74,
    "pilz_ektomykorrhiza": 44.58,
    "wolf_rudel_jagd": 2.45
  },
  "fitness": 0.4557859579165008,
  "timestamp": "20260412_021822",
  "graph_data": {
    "directed": true,
    "multigraph": false,
    "graph": {},
    "nodes": [
      {
        "type": "StandardMLP",
        "bio_influence": {
          "virus_mutationsdruck": 3.26,
          "fledermaus_echolot": 0.0,
          "bienen_schwarm": 5.0,
          "elefanten_matriarchat": 6.33,
          "honigbienentanz": 16.87,
          "ameisen_blattschneider": 19.76,
          "mensch_gehirn": 1.74,
          "pilz_ektomykorrhiza": 44.58,
          "wolf_rudel_jagd": 2.45
        },
        "id": 0
      },
      {
        "type": "PlasticityGate",
        "bio_influence": {
          "virus_mutationsdruck": 3.26,
          "fledermaus_echolot": 0.0,
          "bienen_schwarm": 5.0,
          "elefanten_matriarchat": 6.33,
          "honigbienentanz": 16.87,
          "ameisen_blattschneider": 19.76,
          "mensch_gehirn": 1.74,
          "pilz_ektomykorrhiza": 44.58,
          "wolf_rudel_jagd": 2.45
        },
        "id": 1
      },
      {
        "type": "PlasticityGate",
        "bio_influence": {
          "virus_mutationsdruck": 3.26,
          "fledermaus_echolot": 0.0,
          "bienen_schwarm": 5.0,
          "elefanten_matriarchat": 6.33,
          "honigbienentanz": 16.87,
          "ameisen_blattschneider": 19.76,
          "mensch_gehirn": 1.74,
          "pilz_ektomykorrhiza": 44.58,
          "wolf_rudel_jagd": 2.45
        },
        "id": 2
      },
      {
        "type": "PlasticityGate",
        "bio_influence": {
          "virus_mutationsdruck": 3.26,
          "fledermaus_echolot": 0.0,
          "bienen_schwarm": 5.0,
          "elefanten_matriarchat": 6.33,
          "honigbienentanz": 16.87,
          "ameisen_blattschneider": 19.76,
          "mensch_gehirn": 1.74,
          "pilz_ektomykorrhiza": 44.58,
          "wolf_rudel_jagd": 2.45
        },
        "id": 3
      },
      {
        "type": "StandardMLP",
        "bio_influence": {
          "virus_mutationsdruck": 3.26,
          "fledermaus_echolot": 0.0,
          "bienen_schwarm": 5.0,
          "elefanten_matriarchat": 6.33,
          "honigbienentanz": 16.87,
          "ameisen_blattschneider": 19.76,
          "mensch_gehirn": 1.74,
          "pilz_ektomykorrhiza": 44.58,
          "wolf_rudel_jagd": 2.45
        },
        "id": 4
      },
      {
        "type": "PlasticityGate",
        "bio_influence": {
          "virus_mutationsdruck": 3.26,
          "fledermaus_echolot": 0.0,
          "bienen_schwarm": 5.0,
          "elefanten_matriarchat": 6.33,
          "honigbienentanz": 16.87,
          "ameisen_blattschneider": 19.76,
          "mensch_gehirn": 1.74,
          "pilz_ektomykorrhiza": 44.58,
          "wolf_rudel_jagd": 2.45
        },
        "id": 5
      },
      {
        "type": "PlasticityGate",
        "bio_influence": {
          "virus_mutationsdruck": 3.26,
          "fledermaus_echolot": 0.0,
          "bienen_schwarm": 5.0,
          "elefanten_matriarchat": 6.33,
          "honigbienentanz": 16.87,
          "ameisen_blattschneider": 19.76,
          "mensch_gehirn": 1.74,
          "pilz_ektomykorrhiza": 44.58,
          "wolf_rudel_jagd": 2.45
        },
        "id": 6
      },
      {
        "type": "PlasticityGate",
        "bio_influence": {
          "virus_mutationsdruck": 3.26,
          "fledermaus_echolot": 0.0,
          "bienen_schwarm": 5.0,
          "elefanten_matriarchat": 6.33,
          "honigbienentanz": 16.87,
          "ameisen_blattschneider": 19.76,
          "mensch_gehirn": 1.74,
          "pilz_ektomykorrhiza": 44.58,
          "wolf_rudel_jagd": 2.45
        },
        "id": 7
      },
      {
        "type": "PlasticityGate",
        "bio_influence": {
          "virus_mutationsdruck": 3.26,
          "fledermaus_echolot": 0.0,
          "bienen_schwarm": 5.0,
          "elefanten_matriarchat": 6.33,
          "honigbienentanz": 16.87,
          "ameisen_blattschneider": 19.76,
          "mensch_gehirn": 1.74,
          "pilz_ektomykorrhiza": 44.58,
          "wolf_rudel_jagd": 2.45
        },
        "id": 8
      },
      {
        "type": "PlasticityGate",
        "bio_influence": {
          "virus_mutationsdruck": 3.26,
          "fledermaus_echolot": 0.0,
          "bienen_schwarm": 5.0,
          "elefanten_matriarchat": 6.33,
          "honigbienentanz": 16.87,
          "ameisen_blattschneider": 19.76,
          "mensch_gehirn": 1.74,
          "pilz_ektomykorrhiza": 44.58,
          "wolf_rudel_jagd": 2.45
        },
        "id": 9
      },
      {
        "type": "StandardMLP",
        "bio_influence": {
          "virus_mutationsdruck": 3.26,
          "fledermaus_echolot": 0.0,
          "bienen_schwarm": 5.0,
          "elefanten_matriarchat": 6.33,
          "honigbienentanz": 16.87,
          "ameisen_blattschneider": 19.76,
          "mensch_gehirn": 1.74,
          "pilz_ektomykorrhiza": 44.58,
          "wolf_rudel_jagd": 2.45
        },
        "id": 10
      },
      {
        "type": "PlasticityGate",
        "bio_influence": {
          "virus_mutationsdruck": 3.26,
          "fledermaus_echolot": 0.0,
          "bienen_schwarm": 5.0,
          "elefanten_matriarchat": 6.33,
          "honigbienentanz": 16.87,
          "ameisen_blattschneider": 19.76,
          "mensch_gehirn": 1.74,
          "pilz_ektomykorrhiza": 44.58,
          "wolf_rudel_jagd": 2.45
        },
        "id": 11
      },
      {
        "type": "PlasticityGate",
        "bio_influence": {
          "virus_mutationsdruck": 3.26,
          "fledermaus_echolot": 0.0,
          "bienen_schwarm": 5.0,
          "elefanten_matriarchat": 6.33,
          "honigbienentanz": 16.87,
          "ameisen_blattschneider": 19.76,
          "mensch_gehirn": 1.74,
          "pilz_ektomykorrhiza": 44.58,
          "wolf_rudel_jagd": 2.45
        },
        "id": 12
      },
      {
        "type": "PlasticityGate",
        "bio_influence": {
          "virus_mutationsdruck": 3.26,
          "fledermaus_echolot": 0.0,
          "bienen_schwarm": 5.0,
          "elefanten_matriarchat": 6.33,
          "honigbienentanz": 16.87,
          "ameisen_blattschneider": 19.76,
          "mensch_gehirn": 1.74,
          "pilz_ektomykorrhiza": 44.58,
          "wolf_rudel_jagd": 2.45
        },
        "id": 13
      },
      {
        "type": "PlasticityGate",
        "bio_influence": {
          "virus_mutationsdruck": 3.26,
          "fledermaus_echolot": 0.0,
          "bienen_schwarm": 5.0,
          "elefanten_matriarchat": 6.33,
          "honigbienentanz": 16.87,
          "ameisen_blattschneider": 19.76,
          "mensch_gehirn": 1.74,
          "pilz_ektomykorrhiza": 44.58,
          "wolf_rudel_jagd": 2.45
        },
        "id": 14
      },
      {
        "type": "PlasticityGate",
        "bio_influence": {
          "virus_mutationsdruck": 3.26,
          "fledermaus_echolot": 0.0,
          "bienen_schwarm": 5.0,
          "elefanten_matriarchat": 6.33,
          "honigbienentanz": 16.87,
          "ameisen_blattschneider": 19.76,
          "mensch_gehirn": 1.74,
          "pilz_ektomykorrhiza": 44.58,
          "wolf_rudel_jagd": 2.45
        },
        "id": 15
      },
      {
        "type": "StandardMLP",
        "bio_influence": {
          "virus_mutationsdruck": 3.26,
          "fledermaus_echolot": 0.0,
          "bienen_schwarm": 5.0,
          "elefanten_matriarchat": 6.33,
          "honigbienentanz": 16.87,
          "ameisen_blattschneider": 19.76,
          "mensch_gehirn": 1.74,
          "pilz_ektomykorrhiza": 44.58,
          "wolf_rudel_jagd": 2.45
        },
        "id": 16
      },
      {
        "type": "PlasticityGate",
        "bio_influence": {
          "virus_mutationsdruck": 3.26,
          "fledermaus_echolot": 0.0,
          "bienen_schwarm": 5.0,
          "elefanten_matriarchat": 6.33,
          "honigbienentanz": 16.87,
          "ameisen_blattschneider": 19.76,
          "mensch_gehirn": 1.74,
          "pilz_ektomykorrhiza": 44.58,
          "wolf_rudel_jagd": 2.45
        },
        "id": 17
      },
      {
        "type": "StandardMLP",
        "bio_influence": {
          "virus_mutationsdruck": 3.26,
          "fledermaus_echolot": 0.0,
          "bienen_schwarm": 5.0,
          "elefanten_matriarchat": 6.33,
          "honigbienentanz": 16.87,
          "ameisen_blattschneider": 19.76,
          "mensch_gehirn": 1.74,
          "pilz_ektomykorrhiza": 44.58,
          "wolf_rudel_jagd": 2.45
        },
        "id": 18
      },
      {
        "type": "StandardMLP",
        "bio_influence": {
          "virus_mutationsdruck": 3.26,
          "fledermaus_echolot": 0.0,
          "bienen_schwarm": 5.0,
          "elefanten_matriarchat": 6.33,
          "honigbienentanz": 16.87,
          "ameisen_blattschneider": 19.76,
          "mensch_gehirn": 1.74,
          "pilz_ektomykorrhiza": 44.58,
          "wolf_rudel_jagd": 2.45
        },
        "id": 19
      },
      {
        "type": "StandardMLP",
        "bio_influence": {
          "virus_mutationsdruck": 3.26,
          "fledermaus_echolot": 0.0,
          "bienen_schwarm": 5.0,
          "elefanten_matriarchat": 6.33,
          "honigbienentanz": 16.87,
          "ameisen_blattschneider": 19.76,
          "mensch_gehirn": 1.74,
          "pilz_ektomykorrhiza": 44.58,
          "wolf_rudel_jagd": 2.45
        },
        "id": 20
      },
      {
        "type": "StandardMLP",
        "bio_influence": {
          "virus_mutationsdruck": 3.26,
          "fledermaus_echolot": 0.0,
          "bienen_schwarm": 5.0,
          "elefanten_matriarchat": 6.33,
          "honigbienentanz": 16.87,
          "ameisen_blattschneider": 19.76,
          "mensch_gehirn": 1.74,
          "pilz_ektomykorrhiza": 44.58,
          "wolf_rudel_jagd": 2.45
        },
        "id": 21
      },
      {
        "type": "StandardMLP",
        "bio_influence": {
          "virus_mutationsdruck": 3.26,
          "fledermaus_echolot": 0.0,
          "bienen_schwarm": 5.0,
          "elefanten_matriarchat": 6.33,
          "honigbienentanz": 16.87,
          "ameisen_blattschneider": 19.76,
          "mensch_gehirn": 1.74,
          "pilz_ektomykorrhiza": 44.58,
          "wolf_rudel_jagd": 2.45
        },
        "id": 22
      },
      {
        "type": "PlasticityGate",
        "bio_influence": {
          "virus_mutationsdruck": 3.26,
          "fledermaus_echolot": 0.0,
          "bienen_schwarm": 5.0,
          "elefanten_matriarchat": 6.33,
          "honigbienentanz": 16.87,
          "ameisen_blattschneider": 19.76,
          "mensch_gehirn": 1.74,
          "pilz_ektomykorrhiza": 44.58,
          "wolf_rudel_jagd": 2.45
        },
        "id": 23
      },
      {
        "type": "StandardMLP",
        "bio_influence": {
          "virus_mutationsdruck": 3.26,
          "fledermaus_echolot": 0.0,
          "bienen_schwarm": 5.0,
          "elefanten_matriarchat": 6.33,
          "honigbienentanz": 16.87,
          "ameisen_blattschneider": 19.76,
          "mensch_gehirn": 1.74,
          "pilz_ektomykorrhiza": 44.58,
          "wolf_rudel_jagd": 2.45
        },
        "id": 24
      },
      {
        "type": "PlasticityGate",
        "bio_influence": {
          "virus_mutationsdruck": 3.26,
          "fledermaus_echolot": 0.0,
          "bienen_schwarm": 5.0,
          "elefanten_matriarchat": 6.33,
          "honigbienentanz": 16.87,
          "ameisen_blattschneider": 19.76,
          "mensch_gehirn": 1.74,
          "pilz_ektomykorrhiza": 44.58,
          "wolf_rudel_jagd": 2.45
        },
        "id": 25
      },
      {
        "type": "StandardMLP",
        "bio_influence": {
          "virus_mutationsdruck": 3.26,
          "fledermaus_echolot": 0.0,
          "bienen_schwarm": 5.0,
          "elefanten_matriarchat": 6.33,
          "honigbienentanz": 16.87,
          "ameisen_blattschneider": 19.76,
          "mensch_gehirn": 1.74,
          "pilz_ektomykorrhiza": 44.58,
          "wolf_rudel_jagd": 2.45
        },
        "id": 26
      },
      {
        "type": "AttentionHead",
        "bio_influence": {
          "virus_mutationsdruck": 3.26,
          "fledermaus_echolot": 0.0,
          "bienen_schwarm": 5.0,
          "elefanten_matriarchat": 6.33,
          "honigbienentanz": 16.87,
          "ameisen_blattschneider": 19.76,
          "mensch_gehirn": 1.74,
          "pilz_ektomykorrhiza": 44.58,
          "wolf_rudel_jagd": 2.45
        },
        "id": 27
      },
      {
        "type": "PlasticityGate",
        "bio_influence": {
          "virus_mutationsdruck": 3.26,
          "fledermaus_echolot": 0.0,
          "bienen_schwarm": 5.0,
          "elefanten_matriarchat": 6.33,
          "honigbienentanz": 16.87,
          "ameisen_blattschneider": 19.76,
          "mensch_gehirn": 1.74,
          "pilz_ektomykorrhiza": 44.58,
          "wolf_rudel_jagd": 2.45
        },
        "id": 28
      },
      {
        "type": "PlasticityGate",
        "bio_influence": {
          "virus_mutationsdruck": 3.26,
          "fledermaus_echolot": 0.0,
          "bienen_schwarm": 5.0,
          "elefanten_matriarchat": 6.33,
          "honigbienentanz": 16.87,
          "ameisen_blattschneider": 19.76,
          "mensch_gehirn": 1.74,
          "pilz_ektomykorrhiza": 44.58,
          "wolf_rudel_jagd": 2.45
        },
        "id": 29
      },
      {
        "type": "PlasticityGate",
        "bio_influence": {
          "virus_mutationsdruck": 3.26,
          "fledermaus_echolot": 0.0,
          "bienen_schwarm": 5.0,
          "elefanten_matriarchat": 6.33,
          "honigbienentanz": 16.87,
          "ameisen_blattschneider": 19.76,
          "mensch_gehirn": 1.74,
          "pilz_ektomykorrhiza": 44.58,
          "wolf_rudel_jagd": 2.45
        },
        "id": 30
      },
      {
        "type": "PlasticityGate",
        "bio_influence": {
          "virus_mutationsdruck": 3.26,
          "fledermaus_echolot": 0.0,
          "bienen_schwarm": 5.0,
          "elefanten_matriarchat": 6.33,
          "honigbienentanz": 16.87,
          "ameisen_blattschneider": 19.76,
          "mensch_gehirn": 1.74,
          "pilz_ektomykorrhiza": 44.58,
          "wolf_rudel_jagd": 2.45
        },
        "id": 31
      },
      {
        "type": "StandardMLP",
        "bio_influence": {
          "virus_mutationsdruck": 3.26,
          "fledermaus_echolot": 0.0,
          "bienen_schwarm": 5.0,
          "elefanten_matriarchat": 6.33,
          "honigbienentanz": 16.87,
          "ameisen_blattschneider": 19.76,
          "mensch_gehirn": 1.74,
          "pilz_ektomykorrhiza": 44.58,
          "wolf_rudel_jagd": 2.45
        },
        "id": 32
      },
      {
        "type": "PlasticityGate",
        "bio_influence": {
          "virus_mutationsdruck": 3.26,
          "fledermaus_echolot": 0.0,
          "bienen_schwarm": 5.0,
          "elefanten_matriarchat": 6.33,
          "honigbienentanz": 16.87,
          "ameisen_blattschneider": 19.76,
          "mensch_gehirn": 1.74,
          "pilz_ektomykorrhiza": 44.58,
          "wolf_rudel_jagd": 2.45
        },
        "id": 33
      }
    ],
    "edges": [
      {
        "weight": 1.3400969335915884,
        "type": "forward",
        "source": 0,
        "target": 1
      },
      {
        "weight": 0.522397941999228,
        "type": "forward",
        "source": 0,
        "target": 2
      },
      {
        "weight": 1.0487737417131764,
        "type": "forward",
        "source": 0,
        "target": 4
      },
      {
        "weight": 0.4924376777042993,
        "type": "feedback",
        "source": 0,
        "target": 6
      },
      {
        "weight": 0.8974003883493853,
        "type": "forward",
        "source": 0,
        "target": 8
      },
      {
        "weight": 0.8760250718550622,
        "type": "forward",
        "source": 0,
        "target": 9
      },
      {
        "weight": 0.8342806976985384,
        "type": "forward",
        "source": 0,
        "target": 19
      },
      {
        "weight": 1.1360747061115952,
        "type": "forward",
        "source": 0,
        "target": 23
      },
      {
        "weight": 0.8936995067611534,
        "type": "forward",
        "source": 0,
        "target": 26
      },
      {
        "weight": 0.5248667962636968,
        "type": "forward",
        "source": 0,
        "target": 29
      },
      {
        "weight": 1.1789034677718635,
        "type": "forward",
        "source": 0,
        "target": 33
      },
      {
        "weight": 1.3247212748391175,
        "type": "forward",
        "source": 1,
        "target": 2
      },
      {
        "weight": 1.458511229171609,
        "type": "forward",
        "source": 1,
        "target": 5
      },
      {
        "weight": 1.44861307379765,
        "type": "forward",
        "source": 1,
        "target": 12
      },
      {
        "weight": 0.765226943654342,
        "type": "forward",
        "source": 1,
        "target": 15
      },
      {
        "weight": 0.958797125676673,
        "type": "forward",
        "source": 1,
        "target": 21
      },
      {
        "weight": 1.2086024774661381,
        "type": "forward",
        "source": 1,
        "target": 23
      },
      {
        "weight": 0.9234788259825811,
        "type": "forward",
        "source": 1,
        "target": 24
      },
      {
        "weight": 0.777694977698563,
        "type": "forward",
        "source": 1,
        "target": 25
      },
      {
        "weight": 1.141792442361818,
        "type": "forward",
        "source": 1,
        "target": 28
      },
      {
        "weight": 0.6124908357222199,
        "type": "forward",
        "source": 1,
        "target": 30
      },
      {
        "weight": 1.3067561059911168,
        "type": "forward",
        "source": 2,
        "target": 6
      },
      {
        "weight": 0.6173147175112529,
        "type": "forward",
        "source": 2,
        "target": 9
      },
      {
        "weight": 0.9842283936399066,
        "type": "forward",
        "source": 2,
        "target": 11
      },
      {
        "weight": 1.2174036501616659,
        "type": "forward",
        "source": 2,
        "target": 25
      },
      {
        "weight": 1.4914420593808,
        "type": "forward",
        "source": 2,
        "target": 28
      },
      {
        "weight": 1.3031650270560768,
        "type": "forward",
        "source": 2,
        "target": 29
      },
      {
        "weight": 1.1280386883283333,
        "type": "forward",
        "source": 2,
        "target": 30
      },
      {
        "weight": 0.6791180649297713,
        "type": "forward",
        "source": 3,
        "target": 6
      },
      {
        "weight": 0.5233909157258568,
        "type": "forward",
        "source": 3,
        "target": 9
      },
      {
        "weight": 0.7013569604126652,
        "type": "forward",
        "source": 3,
        "target": 10
      },
      {
        "weight": 0.575967248689227,
        "type": "forward",
        "source": 3,
        "target": 14
      },
      {
        "weight": 1.0549786263435341,
        "type": "forward",
        "source": 3,
        "target": 15
      },
      {
        "weight": 0.7588086396558621,
        "type": "forward",
        "source": 3,
        "target": 18
      },
      {
        "weight": 0.8714343568348781,
        "type": "forward",
        "source": 3,
        "target": 20
      },
      {
        "weight": 1.4403885095728826,
        "type": "forward",
        "source": 3,
        "target": 23
      },
      {
        "weight": 0.9378751222545728,
        "type": "forward",
        "source": 3,
        "target": 24
      },
      {
        "weight": 0.7254167596090817,
        "type": "forward",
        "source": 3,
        "target": 25
      },
      {
        "weight": 0.9390298416707817,
        "type": "forward",
        "source": 3,
        "target": 26
      },
      {
        "weight": 0.8340621316174486,
        "type": "forward",
        "source": 3,
        "target": 28
      },
      {
        "weight": 1.2000385475198434,
        "type": "forward",
        "source": 3,
        "target": 32
      },
      {
        "weight": 1.415064682038555,
        "type": "forward",
        "source": 3,
        "target": 33
      },
      {
        "weight": 0.6507656505345929,
        "type": "feedback",
        "source": 3,
        "target": 8
      },
      {
        "weight": 0.7386544523350163,
        "type": "forward",
        "source": 4,
        "target": 6
      },
      {
        "weight": 0.569202620826184,
        "type": "feedback",
        "source": 4,
        "target": 11
      },
      {
        "weight": 1.4685858695027312,
        "type": "forward",
        "source": 4,
        "target": 14
      },
      {
        "weight": 1.1440100528998853,
        "type": "forward",
        "source": 4,
        "target": 16
      },
      {
        "weight": 0.5349558226721036,
        "type": "forward",
        "source": 4,
        "target": 18
      },
      {
        "weight": 1.150198984780506,
        "type": "forward",
        "source": 4,
        "target": 27
      },
      {
        "weight": 0.8573598141894531,
        "type": "forward",
        "source": 4,
        "target": 30
      },
      {
        "weight": 1.0203764791275423,
        "type": "forward",
        "source": 4,
        "target": 31
      },
      {
        "weight": 1.198004214816597,
        "type": "forward",
        "source": 4,
        "target": 33
      },
      {
        "weight": 0.5021009448080549,
        "type": "forward",
        "source": 5,
        "target": 8
      },
      {
        "weight": 1.2466396813807243,
        "type": "forward",
        "source": 5,
        "target": 10
      },
      {
        "weight": 0.894122206790068,
        "type": "forward",
        "source": 5,
        "target": 11
      },
      {
        "weight": 0.8270387363328376,
        "type": "forward",
        "source": 5,
        "target": 16
      },
      {
        "weight": 1.1672694474672465,
        "type": "forward",
        "source": 5,
        "target": 20
      },
      {
        "weight": 1.4814688436607768,
        "type": "forward",
        "source": 5,
        "target": 28
      },
      {
        "weight": 1.2921911635519938,
        "type": "forward",
        "source": 5,
        "target": 29
      },
      {
        "weight": 0.7635668073003636,
        "type": "forward",
        "source": 5,
        "target": 30
      },
      {
        "weight": 0.8554202034152067,
        "type": "forward",
        "source": 5,
        "target": 32
      },
      {
        "weight": 0.6784311901596325,
        "type": "forward",
        "source": 6,
        "target": 9
      },
      {
        "weight": 1.0945775798521433,
        "type": "forward",
        "source": 6,
        "target": 13
      },
      {
        "weight": 1.261339296398281,
        "type": "forward",
        "source": 6,
        "target": 20
      },
      {
        "weight": 1.3567082517944762,
        "type": "forward",
        "source": 6,
        "target": 21
      },
      {
        "weight": 1.2885265077207726,
        "type": "forward",
        "source": 6,
        "target": 23
      },
      {
        "weight": 0.6422093532416806,
        "type": "forward",
        "source": 6,
        "target": 32
      },
      {
        "weight": 0.31608927197600617,
        "type": "feedback",
        "source": 6,
        "target": 18
      },
      {
        "weight": 1.1930708737695859,
        "type": "forward",
        "source": 7,
        "target": 23
      },
      {
        "weight": 0.5493745577514025,
        "type": "forward",
        "source": 7,
        "target": 26
      },
      {
        "weight": 1.4714303029062878,
        "type": "forward",
        "source": 7,
        "target": 27
      },
      {
        "weight": 0.5878293657012703,
        "type": "forward",
        "source": 7,
        "target": 28
      },
      {
        "weight": 0.6576154304350215,
        "type": "forward",
        "source": 7,
        "target": 29
      },
      {
        "weight": 0.8292196155765712,
        "type": "forward",
        "source": 7,
        "target": 31
      },
      {
        "weight": 1.0213826467056872,
        "type": "forward",
        "source": 8,
        "target": 9
      },
      {
        "weight": 0.9166762937156374,
        "type": "forward",
        "source": 8,
        "target": 14
      },
      {
        "weight": 0.9352663517099455,
        "type": "forward",
        "source": 8,
        "target": 15
      },
      {
        "weight": 1.345874915826097,
        "type": "forward",
        "source": 8,
        "target": 18
      },
      {
        "weight": 1.4977152702998782,
        "type": "forward",
        "source": 8,
        "target": 21
      },
      {
        "weight": 1.0007712989485567,
        "type": "forward",
        "source": 8,
        "target": 29
      },
      {
        "weight": 1.0262473362324278,
        "type": "forward",
        "source": 8,
        "target": 31
      },
      {
        "weight": 1.0464150291346077,
        "type": "forward",
        "source": 9,
        "target": 10
      },
      {
        "weight": 0.7921544890876547,
        "type": "forward",
        "source": 9,
        "target": 11
      },
      {
        "weight": 1.4516372946843639,
        "type": "forward",
        "source": 9,
        "target": 13
      },
      {
        "weight": 1.366878376004534,
        "type": "forward",
        "source": 9,
        "target": 14
      },
      {
        "weight": 0.7071824225351228,
        "type": "forward",
        "source": 9,
        "target": 15
      },
      {
        "weight": 0.8866798109176256,
        "type": "forward",
        "source": 9,
        "target": 16
      },
      {
        "weight": 1.0830646494894247,
        "type": "forward",
        "source": 9,
        "target": 17
      },
      {
        "weight": 0.7079630842027498,
        "type": "forward",
        "source": 9,
        "target": 18
      },
      {
        "weight": 0.8651148211209175,
        "type": "forward",
        "source": 9,
        "target": 19
      },
      {
        "weight": 0.6619725513920721,
        "type": "forward",
        "source": 9,
        "target": 20
      },
      {
        "weight": 0.6534702722420911,
        "type": "forward",
        "source": 9,
        "target": 21
      },
      {
        "weight": 1.2632223414724997,
        "type": "forward",
        "source": 9,
        "target": 22
      },
      {
        "weight": 1.1660442587412156,
        "type": "forward",
        "source": 9,
        "target": 25
      },
      {
        "weight": 0.5996448017512953,
        "type": "forward",
        "source": 9,
        "target": 27
      },
      {
        "weight": 1.132706974731371,
        "type": "forward",
        "source": 10,
        "target": 14
      },
      {
        "weight": 1.058459429183248,
        "type": "forward",
        "source": 10,
        "target": 16
      },
      {
        "weight": 1.0811967731404386,
        "type": "forward",
        "source": 10,
        "target": 17
      },
      {
        "weight": 0.5844535958775214,
        "type": "forward",
        "source": 10,
        "target": 19
      },
      {
        "weight": 0.5311911974670562,
        "type": "forward",
        "source": 10,
        "target": 22
      },
      {
        "weight": 1.3524942598603138,
        "type": "forward",
        "source": 10,
        "target": 27
      },
      {
        "weight": 0.9083385519495402,
        "type": "forward",
        "source": 10,
        "target": 29
      },
      {
        "weight": 1.2780492443304245,
        "type": "forward",
        "source": 10,
        "target": 31
      },
      {
        "weight": 0.6970728731499803,
        "type": "forward",
        "source": 10,
        "target": 32
      },
      {
        "weight": 0.6350693820390442,
        "type": "forward",
        "source": 11,
        "target": 12
      },
      {
        "weight": 1.3494166646273986,
        "type": "forward",
        "source": 11,
        "target": 19
      },
      {
        "weight": 0.5248989080215022,
        "type": "forward",
        "source": 11,
        "target": 25
      },
      {
        "weight": 0.9928504545036552,
        "type": "forward",
        "source": 11,
        "target": 26
      },
      {
        "weight": 1.114800658332558,
        "type": "forward",
        "source": 11,
        "target": 27
      },
      {
        "weight": 0.8764524154494353,
        "type": "forward",
        "source": 12,
        "target": 13
      },
      {
        "weight": 1.31218578548848,
        "type": "forward",
        "source": 12,
        "target": 15
      },
      {
        "weight": 0.7927326770373013,
        "type": "forward",
        "source": 12,
        "target": 20
      },
      {
        "weight": 1.365798368776308,
        "type": "forward",
        "source": 12,
        "target": 23
      },
      {
        "weight": 1.3867227237282749,
        "type": "forward",
        "source": 12,
        "target": 24
      },
      {
        "weight": 0.5446194877996847,
        "type": "forward",
        "source": 12,
        "target": 27
      },
      {
        "weight": 0.9804469921909191,
        "type": "forward",
        "source": 12,
        "target": 28
      },
      {
        "weight": 1.2427450239829176,
        "type": "forward",
        "source": 12,
        "target": 33
      },
      {
        "weight": 0.6746378407345743,
        "type": "forward",
        "source": 13,
        "target": 15
      },
      {
        "weight": 0.952583541176492,
        "type": "forward",
        "source": 13,
        "target": 20
      },
      {
        "weight": 1.447125796194649,
        "type": "forward",
        "source": 13,
        "target": 23
      },
      {
        "weight": 0.9628841977597008,
        "type": "forward",
        "source": 13,
        "target": 24
      },
      {
        "weight": 1.070573183591271,
        "type": "forward",
        "source": 13,
        "target": 26
      },
      {
        "weight": 0.7321730720961485,
        "type": "forward",
        "source": 13,
        "target": 31
      },
      {
        "weight": 1.3974976628761135,
        "type": "forward",
        "source": 13,
        "target": 33
      },
      {
        "weight": 1.2263897844160025,
        "type": "forward",
        "source": 14,
        "target": 16
      },
      {
        "weight": 0.9763862526093817,
        "type": "forward",
        "source": 14,
        "target": 18
      },
      {
        "weight": 0.7241954115964973,
        "type": "forward",
        "source": 14,
        "target": 30
      },
      {
        "weight": 0.9678181653851572,
        "type": "forward",
        "source": 15,
        "target": 19
      },
      {
        "weight": 1.0155846505583703,
        "type": "forward",
        "source": 15,
        "target": 20
      },
      {
        "weight": 1.420331944978111,
        "type": "forward",
        "source": 15,
        "target": 22
      },
      {
        "weight": 1.280972861588555,
        "type": "forward",
        "source": 15,
        "target": 23
      },
      {
        "weight": 1.0238998601054456,
        "type": "forward",
        "source": 15,
        "target": 27
      },
      {
        "weight": 0.6187347634504599,
        "type": "forward",
        "source": 15,
        "target": 29
      },
      {
        "weight": 1.1824245663932906,
        "type": "forward",
        "source": 15,
        "target": 32
      },
      {
        "weight": 0.9966496756651881,
        "type": "forward",
        "source": 16,
        "target": 19
      },
      {
        "weight": 1.2511617160543462,
        "type": "forward",
        "source": 16,
        "target": 21
      },
      {
        "weight": 1.350935909029209,
        "type": "forward",
        "source": 16,
        "target": 22
      },
      {
        "weight": 0.8990741766090418,
        "type": "forward",
        "source": 16,
        "target": 24
      },
      {
        "weight": 0.529361417043441,
        "type": "forward",
        "source": 16,
        "target": 25
      },
      {
        "weight": 0.8321827103144585,
        "type": "forward",
        "source": 16,
        "target": 30
      },
      {
        "weight": 0.9000904175925877,
        "type": "forward",
        "source": 16,
        "target": 31
      },
      {
        "weight": 0.6718723731721554,
        "type": "forward",
        "source": 17,
        "target": 32
      },
      {
        "weight": 0.536306330589351,
        "type": "forward",
        "source": 18,
        "target": 19
      },
      {
        "weight": 0.9072727205812927,
        "type": "forward",
        "source": 18,
        "target": 20
      },
      {
        "weight": 0.839379304918791,
        "type": "forward",
        "source": 18,
        "target": 24
      },
      {
        "weight": 1.3535484472118227,
        "type": "forward",
        "source": 18,
        "target": 25
      },
      {
        "weight": 1.3135734470689449,
        "type": "forward",
        "source": 18,
        "target": 29
      },
      {
        "weight": 0.6235969874325256,
        "type": "feedback",
        "source": 18,
        "target": 32
      },
      {
        "weight": 1.0455074963906021,
        "type": "forward",
        "source": 19,
        "target": 21
      },
      {
        "weight": 1.4314201861244171,
        "type": "forward",
        "source": 19,
        "target": 22
      },
      {
        "weight": 0.8280685591568413,
        "type": "forward",
        "source": 19,
        "target": 25
      },
      {
        "weight": 1.155841753631222,
        "type": "forward",
        "source": 20,
        "target": 26
      },
      {
        "weight": 0.8949179599587679,
        "type": "forward",
        "source": 20,
        "target": 27
      },
      {
        "weight": 1.0814226054862721,
        "type": "forward",
        "source": 20,
        "target": 31
      },
      {
        "weight": 0.6820866120937621,
        "type": "forward",
        "source": 20,
        "target": 32
      },
      {
        "weight": 1.4151155454539301,
        "type": "forward",
        "source": 21,
        "target": 22
      },
      {
        "weight": 0.5797086000619168,
        "type": "forward",
        "source": 21,
        "target": 23
      },
      {
        "weight": 0.6482966318714505,
        "type": "forward",
        "source": 21,
        "target": 25
      },
      {
        "weight": 1.230976893251377,
        "type": "forward",
        "source": 21,
        "target": 33
      },
      {
        "weight": 1.409257106140137,
        "type": "forward",
        "source": 22,
        "target": 26
      },
      {
        "weight": 0.6158937171266403,
        "type": "forward",
        "source": 22,
        "target": 29
      },
      {
        "weight": 0.7443658391151217,
        "type": "forward",
        "source": 22,
        "target": 32
      },
      {
        "weight": 1.3068800291802558,
        "type": "forward",
        "source": 23,
        "target": 30
      },
      {
        "weight": 1.126007738633385,
        "type": "forward",
        "source": 23,
        "target": 33
      },
      {
        "weight": 0.7521958442592591,
        "type": "forward",
        "source": 24,
        "target": 27
      },
      {
        "weight": 0.6001246855084549,
        "type": "forward",
        "source": 24,
        "target": 30
      },
      {
        "weight": 0.8345282023187057,
        "type": "forward",
        "source": 24,
        "target": 31
      },
      {
        "weight": 1.286179194733744,
        "type": "forward",
        "source": 26,
        "target": 28
      },
      {
        "weight": 1.1707850352152753,
        "type": "forward",
        "source": 26,
        "target": 31
      },
      {
        "weight": 1.4807434290928023,
        "type": "forward",
        "source": 26,
        "target": 33
      },
      {
        "weight": 1.458759937605141,
        "type": "forward",
        "source": 27,
        "target": 31
      },
      {
        "weight": 1.222318065928067,
        "type": "forward",
        "source": 27,
        "target": 32
      },
      {
        "weight": 1.325722656545007,
        "type": "forward",
        "source": 28,
        "target": 30
      },
      {
        "weight": 0.894973047200152,
        "type": "forward",
        "source": 28,
        "target": 31
      },
      {
        "weight": 1.4852700245816703,
        "type": "forward",
        "source": 28,
        "target": 32
      },
      {
        "weight": 0.6756465205033686,
        "type": "forward",
        "source": 30,
        "target": 33
      }
    ]
  }
}